privacy_estimates/__init__.py
privacy_estimates/binomial_proportion.py
privacy_estimates/joint_density.py
privacy_estimates/privacy_region.py
privacy_estimates/utils.py
privacy_estimates-0.1.0.post1.data/scripts/estimate-epsilon.py
privacy_estimates-0.1.0.post1.dist-info/LICENSE
privacy_estimates-0.1.0.post1.dist-info/METADATA
privacy_estimates-0.1.0.post1.dist-info/WHEEL
privacy_estimates-0.1.0.post1.dist-info/top_level.txt
privacy_estimates-0.1.0.post1.dist-info/RECORD
