Metadata-Version: 2.1
Name: privacy-estimates
Version: 0.1.0.post1
Summary: Empirical Privacy Estimates
Home-page: https://github.com/microsoft/privacy-estimates
License-File: LICENSE
Requires-Dist: statsmodels
Requires-Dist: numpy
Requires-Dist: scipy
Requires-Dist: multimethod
Requires-Dist: pydantic-cli
Provides-Extra: dev
Requires-Dist: pytest ; extra == 'dev'
Requires-Dist: sympy ; extra == 'dev'
